neutron_tempest_plugin/README.rst
neutron_tempest_plugin/__init__.py
neutron_tempest_plugin/config.py
neutron_tempest_plugin/exceptions.py
neutron_tempest_plugin/plugin.py
neutron_tempest_plugin/api/__init__.py
neutron_tempest_plugin/api/base.py
neutron_tempest_plugin/api/base_routers.py
neutron_tempest_plugin/api/base_security_groups.py
neutron_tempest_plugin/api/clients.py
neutron_tempest_plugin/api/test_address_groups.py
neutron_tempest_plugin/api/test_address_scopes.py
neutron_tempest_plugin/api/test_address_scopes_negative.py
neutron_tempest_plugin/api/test_auto_allocated_topology.py
neutron_tempest_plugin/api/test_availability_zones.py
neutron_tempest_plugin/api/test_conntrack_helper.py
neutron_tempest_plugin/api/test_extension_driver_port_security.py
neutron_tempest_plugin/api/test_extensions.py
neutron_tempest_plugin/api/test_flavors_extensions.py
neutron_tempest_plugin/api/test_floating_ips.py
neutron_tempest_plugin/api/test_floating_ips_negative.py
neutron_tempest_plugin/api/test_local_ip.py
neutron_tempest_plugin/api/test_metering_extensions.py
neutron_tempest_plugin/api/test_metering_negative.py
neutron_tempest_plugin/api/test_ndp_proxy.py
neutron_tempest_plugin/api/test_ndp_proxy_negative.py
neutron_tempest_plugin/api/test_network_ip_availability.py
neutron_tempest_plugin/api/test_network_ip_availability_negative.py
neutron_tempest_plugin/api/test_networks.py
neutron_tempest_plugin/api/test_networks_negative.py
neutron_tempest_plugin/api/test_port_forwarding_negative.py
neutron_tempest_plugin/api/test_port_forwardings.py
neutron_tempest_plugin/api/test_ports.py
neutron_tempest_plugin/api/test_ports_negative.py
neutron_tempest_plugin/api/test_qos.py
neutron_tempest_plugin/api/test_qos_negative.py
neutron_tempest_plugin/api/test_revisions.py
neutron_tempest_plugin/api/test_router_interface_fip.py
neutron_tempest_plugin/api/test_routers.py
neutron_tempest_plugin/api/test_routers_negative.py
neutron_tempest_plugin/api/test_security_groups.py
neutron_tempest_plugin-3.0.0.dist-info/AUTHORS
neutron_tempest_plugin-3.0.0.dist-info/LICENSE
neutron_tempest_plugin-3.0.0.dist-info/METADATA
neutron_tempest_plugin-3.0.0.dist-info/WHEEL
neutron_tempest_plugin-3.0.0.dist-info/entry_points.txt
neutron_tempest_plugin-3.0.0.dist-info/pbr.json
neutron_tempest_plugin-3.0.0.dist-info/top_level.txt
neutron_tempest_plugin-3.0.0.dist-info/RECORD
