Metadata-Version: 2.1
Name: neutron-tempest-plugin
Version: 3.0.0
Summary: Tempest plugin for Neutron Project
Home-page: https://opendev.org/openstack/neutron-tempest-plugin
Author: OpenStack
Author-email: openstack-discuss@lists.openstack.org
Classifier: Environment :: OpenStack
Classifier: Intended Audience :: Information Technology
Classifier: Intended Audience :: System Administrators
Classifier: License :: OSI Approved :: Apache Software License
Classifier: Operating System :: POSIX :: Linux
Classifier: Programming Language :: Python
Classifier: Programming Language :: Python :: 3
Classifier: Programming Language :: Python :: 3.9
Classifier: Programming Language :: Python :: 3.10
Classifier: Programming Language :: Python :: 3.11
Classifier: Programming Language :: Python :: 3.12
Requires-Python: >=3.9
License-File: LICENSE
License-File: AUTHORS
Requires-Dist: pbr >=3.0.0
Requires-Dist: neutron-lib >=3.21.1
Requires-Dist: oslo.config >=5.2.0
Requires-Dist: netaddr >=0.7.18
Requires-Dist: os-ken >=0.3.0
Requires-Dist: oslo.log >=3.36.0
Requires-Dist: oslo.serialization >=2.20.0
Requires-Dist: oslo.utils >=3.33.0
Requires-Dist: packaging >=20.4
Requires-Dist: paramiko >=2.0.0
Requires-Dist: tempest >=29.2.0
Requires-Dist: tenacity >=3.2.1
Requires-Dist: ddt >=1.0.1
Requires-Dist: testtools >=2.2.0
Requires-Dist: debtcollector >=1.2.0
